<?xml version="1.0" encoding="ISO-8859-1"?>
<root><divID ID="tree_1_1"><Imagename>images/Artocarpus_heterophyllus.jpg</Imagename><sciencename>Artocarpus heterophyllus</sciencename><malayamname>Plavu</malayamname><englishname>Jackfruit</englishname><tamilname>Pilapalam</tamilname><hindiname>Katthal</hindiname><Info>This is a large tree that has the largest fruit in the world. 
                            It is native to the Western Ghats but is now cultivated inmany 
                            others parts of the country</Info><Fresh>-</Fresh><Mature>Dark green</Mature><Size>15-25 cm</Size><Bud>-</Bud><Open>Green</Open><Size>Tiny</Size><Unripe></Unripe><Ripe>Green</Ripe><Shape>Shape</Shape></divID><divID ID="tree_1_2"><Imagename>images/Syzygium_cumini.jpg</Imagename><sciencename>Syzygium cumini</sciencename><malayamname>Njaval</malayamname><englishname>Black plum</englishname><tamilname>Neredam</tamilname><hindiname>Jamun</hindiname><Info>The delicious fruits of this tree stain your mouth black. 
                The leaves, bark and seeds are used in traditional medicine; 
                and the wood is used extensively in construction.</Info><Fresh>Reddish-brown</Fresh><Mature>Green</Mature><Size>7-15 cm</Size><Bud>-</Bud><Open>White</Open><Size>Tiny</Size><Unripe>Green</Unripe><Ripe>Purple-black</Ripe><Shape>Round</Shape><Size>1-5cm</Size></divID><divID ID="tree_1_3"><Imagename>images/Lagerstroemia_speciosa.jpg</Imagename><sciencename>Lagerstroemia speciosa</sciencename><malayamname>Manimaruthu</malayamname><englishname>Queen's flower, Pride of India</englishname><tamilname>Kadali</tamilname><hindiname>Jarul</hindiname><Info>This is a very beautiful flowering tree with pink rose-like wrinkled flowers in large clusters. 
    Maharashtra has honoured this tree by making its flower the state flower. </Info><Fresh>Pink</Fresh><Mature>Green</Mature><Size>Up to 26 cm</Size><Bud>-</Bud><Open>Pink</Open><Size>7cm, clustered</Size><Unripe>Green</Unripe><Ripe>Black</Ripe><Shape>Round</Shape><Size> 2 cm</Size></divID><divID ID="tree_1_4"><Imagename>images/Phyllanthus_emblica.jpg</Imagename><sciencename>Phyllanthus emblica</sciencename><malayamname>Nelli</malayamname><englishname>Indian Gooseberry</englishname><tamilname>Nelli</tamilname><hindiname>Amla</hindiname><Info>This tree grows wild in forests. The fruit has large quantities of vitamin C,
    and is famously sour in taste.</Info><Fresh>-</Fresh><Mature>Green</Mature><Size>8-12 cm</Size><Bud>-</Bud><Open>Pink/greenish</Open><Size>Small</Size><Unripe>-</Unripe><Ripe>Yellow-green</Ripe><Shape>Round</Shape><Size>2-4 cm</Size></divID><divID ID="tree_1_5"><Imagename>images/Magnolia_campbellii.jpg</Imagename><sciencename>Magnolia campbellii</sciencename><malayamname>-</malayamname><englishname>Campbellii Magnolia</englishname><tamilname>-</tamilname><hindiname>Lal champa</hindiname><Info>A large Himalayan tree with spectacular flowers that is found eastwards of Nepal
and grows in elevations between 2000-3000 m.</Info><Fresh>-</Fresh><Mature>-</Mature><Size>10-23 cm</Size><Bud>-</Bud><Open>White/Dark pink</Open><Size>Large</Size><Unripe>-</Unripe><Ripe>-</Ripe><Shape>Cylindrical</Shape><Size>15-20cm</Size></divID><divID ID="tree_1_6"><Imagename>images/Myrica_esculent.jpg</Imagename><sciencename>Myrica esculenta</sciencename><malayamname>-</malayamname><englishname>Box Myrtle</englishname><tamilname>-</tamilname><hindiname>Kaphal</hindiname><Info>Kaphal is an evergreen tree found throughout the mid-Himalayas, starting from about 1,300 metres and going up to about 2,100 metres.</Info><Fresh>-</Fresh><Mature>Green</Mature><Size>8-15 cm</Size><Bud>-</Bud><Open>Greenish-brown</Open><Size>Tiny, clustered</Size><Unripe>Green</Unripe><Ripe>Brown</Ripe><Shape>Flat, papery</Shape><Size>2 cm</Size></divID><divID ID="tree_1_7"><Imagename>images/Rhododendron_arboreum.jpg</Imagename><sciencename>Rhododendron arboreum</sciencename><malayamname>-</malayamname><englishname>Rhododendron</englishname><tamilname>-</tamilname><hindiname>Burans</hindiname><Info>This small evergreen tree is widely distributed across the Himalayas, 
    and is one of the most famous species of rhododendron.</Info><Fresh>-</Fresh><Mature>Green</Mature><Size>10-20cm</Size><Bud>-</Bud><Open>Crimson-red</Open><Size>50mm</Size><Unripe>-</Unripe><Ripe>-</Ripe><Shape>Capsule</Shape><Size>3 cm</Size></divID><divID ID="tree_2_1"><Imagename>images/Acer_sterculiaceum.jpg</Imagename><sciencename>Acer sterculiaceum</sciencename><malayamname>-</malayamname><englishname>Himalayan Maple,</englishname><tamilname>-</tamilname><hindiname>Kainju</hindiname><Info>This fairly large deciduous tree is found across the Himalayas from Kashmir to Bhutan,
growing at elevations between 2,100 and 3,600 m. The leaves are used for fodder.</Info><Fresh>-</Fresh><Mature>Deep Green</Mature><Size>10-15 cm</Size><Bud>-</Bud><Open>Yellowish </Open><Size>Small</Size><Unripe>-</Unripe><Ripe>Pale brown</Ripe><Shape>Small nuts</Shape><Size>5 cm</Size></divID><divID ID="tree_2_2"><Imagename>images/Mangifera_indica.jpg</Imagename><sciencename>Mangifera indica</sciencename><malayamname>Maavu</malayamname><englishname>Mango</englishname><tamilname>Maanga</tamilname><hindiname>Aam</hindiname><Info>Who doesn't know the mango tree, famed in folk stories and for the flavour of its delectable 
fruit? There are many hundreds of varieties of mango in India.</Info><Fresh>Pink/purple</Fresh><Mature>Deep green</Mature><Size>-</Size><Bud>-</Bud><Open>Yellowish-green</Open><Size>Tiny, clustered</Size><Unripe>Green</Unripe><Ripe>Yellow or red</Ripe><Shape>Mango-shaped!</Shape><Size>-</Size></divID><divID ID="tree_2_3"><Imagename>images/Ficus_benghalensis.jpg</Imagename><sciencename>Ficus benghalensis</sciencename><malayamname>-</malayamname><englishname>Banyan</englishname><tamilname>-</tamilname><hindiname>Bargad</hindiname><Info>The banyan is a nearly evergreen, large, spreading tree with prop-roots 
    coming down from its branches. It is found growing wild in forests all over India. </Info><Fresh>Pink</Fresh><Mature>Deep Green</Mature><Size>14 cm</Size><Bud>-</Bud><Open>-</Open><Size>Figs</Size><Unripe>-</Unripe><Ripe>Deep red</Ripe><Shape>Round</Shape><Size>2 cm</Size></divID><divID ID="tree_2_4"><Imagename>images/Saraca_asoca.jpg</Imagename><sciencename>Saraca asoca</sciencename><malayamname>Ashokam</malayamname><englishname>True Ashok</englishname><tamilname>Ashokam</tamilname><hindiname>Ashoka</hindiname><Info> This evergreen tree is rated by some as one of India's most beautiful trees, 
    with the orange-red flowers in bunches among the dense, dark leaves. 
    It is said that Buddha was born under an Ashoka tree, so this tree is sacred to the Buddhists. 
    Hindus also have many sacred associations with this tree.</Info><Fresh>Pinkish</Fresh><Mature>Green</Mature><Size>-</Size><Bud>-</Bud><Open>Orange-red</Open><Size>Clustered</Size><Unripe>Reddish</Unripe><Ripe>Black</Ripe><Shape>Curved pod</Shape><Size> Up to 25 cm</Size></divID><divID ID="tree_2_5"><Imagename>images/Alstonia_scholaris.jpg</Imagename><sciencename>Alstonia scholaris</sciencename><malayamname>Paala/Ezhilampaala</malayamname><englishname>Devil's tree</englishname><tamilname>Mukumpalai</tamilname><hindiname>Saptaparni / Shaitan ka jhad</hindiname><Info>The name scholaris has come because in olden times the slates that chidren used
    were made from the soft wood of this tree. And the name Devil's tree in English and shaitan ka jhad
    in Hindi have probably come because this tree is shunned by animals because of its poisonous nature.
    </Info><Fresh>-</Fresh><Mature>Green</Mature><Size>Up to 24 cm</Size><Bud>-</Bud><Open>Greenish-white</Open><Size>Small, clustered</Size><Unripe>-</Unripe><Ripe>-</Ripe><Shape>Long, thin</Shape><Size> Up to 40 cm</Size></divID><divID ID="tree_2_6"><Imagename>images/Prunus_cerasoides.jpg</Imagename><sciencename>Prunus cerasoides</sciencename><malayamname>-</malayamname><englishname>Himalayan Cherry</englishname><tamilname>-</tamilname><hindiname>Padam</hindiname><Info>A Himalayan tree found at elevations between 750-2400 m. Beautiful to look at when in full bloom and the fruit is good to eat when ripe.</Info><Fresh>-</Fresh><Mature>Green</Mature><Size>13-25 cm</Size><Bud>-</Bud><Open>Pinkish-white</Open><Size>-</Size><Unripe>Yellow</Unripe><Ripe>Red</Ripe><Shape>Ovoid</Shape><Size>1-1.5 cm</Size></divID><divID ID="tree_3_1"><Imagename>images/Bauhinia_purpurea.jpg</Imagename><sciencename>Bauhinia purpurea</sciencename><malayamname>Mandaram</malayamname><englishname>Purple bauhinia</englishname><tamilname>Nilattiruvatti</tamilname><hindiname>Kaniar</hindiname><Info>	There are many types of Bauhinias and their leaves and flowers look similar.
    It is relatively easy to tell the Purple bauhinia apart because the petals in its flower
    do not overlap. The pods of this tree burst open with a loud sound and the seeds get 
    scattered up to 6 m away. The outer covers of the pods become spiral shaped after the 
    seeds are thrown out.</Info><Fresh>-</Fresh><Mature>Green</Mature><Size>15 cm, camel's hoof</Size><Bud>-</Bud><Open>Pink/violet</Open><Size>5-8 cm</Size><Unripe>Green</Unripe><Ripe>Brown</Ripe><Shape>Long flat pod</Shape><Size> Up to 30 cm</Size></divID><divID ID="tree_3_2"><Imagename>images/Erythrina_indica.jpg</Imagename><sciencename>Erythrina indica</sciencename><malayamname>Mullumurikku</malayamname><englishname>Indian coral tree</englishname><tamilname>Mullumurukku</tamilname><hindiname>Pangra</hindiname><Info>A beautiful ornamental tree that is planted in gardens and parks, the flowers 
    of this tree are bright red and striking. A variety of birds are visitors to the coral 
    tree when it is in flower.The flowers appear when the tree is completely bare of leaves.</Info><Fresh>-</Fresh><Mature>Green</Mature><Size>~20cm, trifoliate</Size><Bud>-</Bud><Open>Brilliant red</Open><Size>4-5 cm, clustered</Size><Unripe>Green</Unripe><Ripe>Black</Ripe><Shape>Long, cylindrical</Shape><Size> Up to 30 cm</Size></divID><divID ID="tree_3_3"><Imagename>images/Butea_monosperma.jpg</Imagename><sciencename>Butea monosperma</sciencename><malayamname>-</malayamname><englishname>Flame of the Forest</englishname><tamilname>-</tamilname><hindiname>Dhak/Palash</hindiname><Info>This tree with large leaves is impossible to miss
    when its leafless branches are lit up with the orange fire of its flowers.</Info><Fresh>-</Fresh><Mature>-</Mature><Size>-</Size><Bud>-</Bud><Open>Orange</Open><Size>-</Size><Unripe>-</Unripe><Ripe>Brown</Ripe><Shape>-</Shape><Size>15-20 cm</Size></divID><divID ID="tree_4_1"><Imagename>images/Cassia_fistula.jpg</Imagename><sciencename>Cassia fistula</sciencename><malayamname>Kanikonna</malayamname><englishname>Indian laburnum</englishname><tamilname>Konnei</tamilname><hindiname>Amaltas</hindiname><Info>This is the State flower of Kerala.</Info><Fresh>Brownish</Fresh><Mature>Green</Mature><Size>Up to 45 cm</Size><Bud>-</Bud><Open>Bright yellow</Open><Size>Clusters up to 60 cm</Size><Unripe>Green</Unripe><Ripe>Yellow</Ripe><Shape>Round, woody</Shape><Size>12-14 cm</Size></divID><divID ID="tree_4_2"><Imagename>images/Pongamia_pinnata.jpg</Imagename><sciencename>Pongamia pinnata</sciencename><malayamname>Ungu</malayamname><englishname>Indian beech</englishname><tamilname>Ponga</tamilname><hindiname>Karanj</hindiname><Info>The seeds, root, bark, leaves and flowers all have various 
    uses in traditional medicine so this is a valuable tree. A reddish oil 
    extracted from the seeds called karanj oil is used to light lamps or as a lubricant for engines.</Info><Fresh>Bright green</Fresh><Mature>Dark green</Mature><Size>~20 cm</Size><Bud>-</Bud><Open>White/pinkish</Open><Size>Clustered</Size><Unripe>Green</Unripe><Ripe>Yellow or greyish brown</Ripe><Shape>Flattened oval, woody</Shape><Size> ~5 cm</Size></divID><divID ID="tree_4_3"><Imagename>images/Tamarindus_indica.jpg</Imagename><sciencename>Tamarindus indica</sciencename><malayamname>Puli</malayamname><englishname>Tamarind</englishname><tamilname>Puli</tamilname><hindiname>Imli</hindiname><Info> This large tree with very small but dense leaves is believed to have come to India from East Africa many centuries ago. 
                        Today it is cultivated all over the warm parts of our country and appears like a local Indian tree.</Info><Fresh>Light green</Fresh><Mature>Dark green</Mature><Size>7-15 cm</Size><Bud>Light pink</Bud><Open>Pale yellow</Open><Size>~15 mm</Size><Unripe>Green</Unripe><Ripe>Brown</Ripe><Shape>Flat and curved</Shape><Size>  Up to 20 cm</Size></divID><divID ID="tree_4_4"><Imagename>images/Juglans_regia.jpg</Imagename><sciencename>Juglans regia</sciencename><malayamname>-</malayamname><englishname>Walnut</englishname><tamilname>-</tamilname><hindiname>Akhrot</hindiname><Info>A Himalayan tree that in forests becomes 
    25-30 m tall with a clear long trunk and is indigenous at elevations between 1400-3500 m.</Info><Fresh>-</Fresh><Mature>Dark green</Mature><Size>25-40 cm</Size><Bud>-</Bud><Open>Green</Open><Size>5-10 cm</Size><Unripe>-</Unripe><Ripe>Green</Ripe><Shape>Ovoid</Shape><Size>5 cm</Size></divID><divID ID="tree_4_5"><Imagename>images/Delonix_regia.jpg</Imagename><sciencename>Delonix regia</sciencename><malayamname>Gulmohur</malayamname><englishname>Flame tree</englishname><tamilname>Gulmohur</tamilname><hindiname>Gulmohur</hindiname><Info>This common tree of roadsides and avenues, with its beautiful flowers,
    is grown all over India, but is a native of the forests of Madagascar.</Info><Fresh>-</Fresh><Mature>Dark green</Mature><Size>-</Size><Bud>-</Bud><Open>Bright red</Open><Size>Up to 12 cm</Size><Unripe>Green</Unripe><Ripe>Brown/black</Ripe><Shape>Flat long pods</Shape><Size>Up to 60 cm</Size></divID><divID ID="tree_4_6"><Imagename>images/Acacia_nilotica.jpg</Imagename><sciencename>Acacia nilotica</sciencename><malayamname>-</malayamname><englishname>Egyptian Mimosa</englishname><tamilname>-</tamilname><hindiname>Babool</hindiname><Info>The babool is a very important tree and you can recognize
    it by its almost black bark or its ball-like yellow flowers or 
    its fruit that looks like a bead necklace or by being pricked by its 5 cm long white thorns.</Info><Fresh>-</Fresh><Mature>-</Mature><Size>up to 5cm</Size><Bud>-</Bud><Open>Bright yellow</Open><Size>tiny, 1 cm</Size><Unripe>-</Unripe><Ripe>Greyish pods</Ripe><Shape>-</Shape><Size>upto 20 cm</Size></divID><divID ID="tree_4_7"><Imagename>images/Azadirachta_indica.jpg</Imagename><sciencename>Azadirachta indica</sciencename><malayamname>-</malayamname><englishname>Margosa</englishname><tamilname>-</tamilname><hindiname>Neem</hindiname><Info>The evergreen Neem trees are commonly planted as shade 
trees along streets but most parts of the tree also have very high medicinal value.</Info><Fresh>-</Fresh><Mature>Dark green</Mature><Size>-</Size><Bud>-</Bud><Open>White</Open><Size>tiny</Size><Unripe>-</Unripe><Ripe>Yellow</Ripe><Shape>-</Shape><Size>2 cm</Size></divID><divID ID="tree_4_8"><Imagename>images/Albizia_lebbeck.jpg</Imagename><sciencename>Albizia lebbeck</sciencename><malayamname>-</malayamname><englishname>East Indian Walnut </englishname><tamilname>-</tamilname><hindiname>Siris</hindiname><Info>If you see a bare looking tree full of straw coloured 20-30 cm long flat 
    pods that make a clattering sound in the slightest breeze you may probably be 
    looking at a Siris. .</Info><Fresh>-</Fresh><Mature>Dark green</Mature><Size>upto 25 cm</Size><Bud>-</Bud><Open>Light Yellow</Open><Size>-</Size><Unripe>-</Unripe><Ripe>Yellow</Ripe><Shape>long flat coloured</Shape><Size>pods 20-30 cm </Size></divID><divID ID="tree_5_1"><Imagename>images/Bombax_ceiba.jpg</Imagename><sciencename>Bombax ceiba</sciencename><malayamname>Mulilavu</malayamname><englishname>Red Silk Cotton</englishname><tamilname>Mulilavu</tamilname><hindiname>Semul</hindiname><Info>This tree has branches coming out in all directions and has many levels 
    at which these branches come out like the ribs of many umbrellas one on top of 
    the other. The large flowers are pollinated by birds, and after they fall on the 
    forest floor, are eaten with relish by wild animals. The woody fruit bursts 
    open to release hundreds of seeds attached to sliky fibres, that are wafted away in the wind.</Info><Fresh>-</Fresh><Mature>Green</Mature><Size>Up to 25 cm</Size><Bud>-</Bud><Open>Red</Open><Size>Large</Size><Unripe>Green</Unripe><Ripe>Brown</Ripe><Shape>Woody capsule</Shape><Size>Up to 18 cm</Size></divID></root>
